sshnpd.py
sshnpd-0.4.15.dist-info/LICENSE
sshnpd-0.4.15.dist-info/METADATA
sshnpd-0.4.15.dist-info/WHEEL
sshnpd-0.4.15.dist-info/entry_points.txt
sshnpd-0.4.15.dist-info/RECORD
