Metadata-Version: 2.1
Name: sshnpd
Version: 0.4.15
Summary: Python implementation of SSH No Ports daemon
Home-page: https://github.com/atsign-foundation/noports
Author: Xavier Lin
Author-email: xavier.lin@atsign.com 
Maintainer: Chris Swan
Maintainer-email: chris@atsign.com
Requires-Python: >=3.10,<4.0
Classifier: Programming Language :: Python :: 3
Classifier: Programming Language :: Python :: 3.10
Classifier: Programming Language :: Python :: 3.11
Classifier: Programming Language :: Python :: 3.12
Requires-Dist: atsdk (==0.2.30)
